consistencybench/__init__.py
consistencybench/generators/__init__.py
consistencybench/generators/base.py
consistencybench/generators/cog.py
consistencybench/generators/prompt_template.py
consistencybench/metrics/__init__.py
consistencybench/metrics/agreement.py
consistencybench/metrics/base.py
consistencybench/metrics/nli.py
consistencybench/metrics/pp.py
consistencybench/metrics/prompt_template.py
consistencybench/metrics/scorer.py
consistencybench/perturbations/__init__.py
consistencybench/perturbations/paraphrase.py
consistencybench/perturbations/prompt_template.py
consistencybench-0.1.3.dist-info/LICENSE
consistencybench-0.1.3.dist-info/METADATA
consistencybench-0.1.3.dist-info/WHEEL
consistencybench-0.1.3.dist-info/RECORD
