Metadata-Version: 2.1
Name: ConsistencyBench
Version: 0.1.3
Summary: Tools and Techniques for Consistency Benchmarking
Author: Harsh Raj
Author-email: harsh777111raj@gmail.com
Requires-Python: >=3.9,<4.0
Classifier: Programming Language :: Python :: 3
Classifier: Programming Language :: Python :: 3.9
Classifier: Programming Language :: Python :: 3.10
Classifier: Programming Language :: Python :: 3.11
Classifier: Programming Language :: Python :: 3.12
Requires-Dist: bert-score (>=0.3.13,<0.4.0)
Requires-Dist: evaluate (>=0.4.1,<0.5.0)
Requires-Dist: langchain (>=0.1.11,<0.2.0)
Requires-Dist: langchain-openai (>=0.0.5,<0.0.6)
Requires-Dist: numpy (>=1.26.4,<2.0.0)
Requires-Dist: openai (>=1.12.0,<2.0.0)
Requires-Dist: python-dotenv (>=1.0.1,<2.0.0)
Requires-Dist: scipy (>=1.12.0,<2.0.0)
Requires-Dist: spacy (>=3.7.4,<4.0.0)
Requires-Dist: tokenizers (>=0.15.2,<0.16.0)
Requires-Dist: transformers (>=4.38.2,<5.0.0)
